ftd2xx/__init__.py
ftd2xx/_ftd2xx.py
ftd2xx/_ftd2xx_darwin.py
ftd2xx/_ftd2xx_linux.py
ftd2xx/defines.py
ftd2xx/ftd2xx.py
ftd2xx/tests/__init__.py
ftd2xx/tests/t_ftd2xx.py
ftd2xx-1.3.5.dist-info/LICENSE
ftd2xx-1.3.5.dist-info/METADATA
ftd2xx-1.3.5.dist-info/WHEEL
ftd2xx-1.3.5.dist-info/top_level.txt
ftd2xx-1.3.5.dist-info/RECORD
