Metadata-Version: 2.1
Name: ftd2xx
Version: 1.3.5
Summary: Python interface to ftd2xx.dll from FTDI using ctypes based on d2xx by Pablo Bleyer
Home-page: https://github.com/snmishra/ftd2xx
Author: Satya Mishra
Author-email: satya.devel@gmail.com
License: MIT License
Keywords: ftd2xx,d2xx,ftdi
Classifier: Programming Language :: Python :: 3
Classifier: License :: OSI Approved :: MIT License
Classifier: Operating System :: OS Independent
License-File: LICENSE
Requires-Dist: pywin32 ; platform_system == "Windows"
Requires-Dist: typing-extensions ; python_version < "3.8"
